docker_droplet/__init__.py
docker_droplet/down.py
docker_droplet/exceptions.py
docker_droplet/main.py
docker_droplet/up.py
docker_droplet/__pycache__/__init__.cpython-36.pyc
docker_droplet/__pycache__/down.cpython-36.pyc
docker_droplet/__pycache__/exceptions.cpython-36.pyc
docker_droplet/__pycache__/main.cpython-36.pyc
docker_droplet/__pycache__/up.cpython-36.pyc
docker_droplet/ansible/__init__.py
docker_droplet/ansible/playbook.yml
docker_droplet/ansible/__pycache__/__init__.cpython-36.pyc
docker_droplet/ansible/inventory/__init__.py
docker_droplet/ansible/inventory/digitalocean.py
docker_droplet/ansible/inventory/__pycache__/__init__.cpython-36.pyc
docker_droplet/ansible/inventory/__pycache__/digitalocean.cpython-36.pyc
docker_droplet/ansible/roles/base/tasks/main.yml
docker_droplet/ansible/roles/docker/meta/main.yml
docker_droplet/ansible/roles/docker/tasks/main.yml
docker_droplet/docs/conf.py
docker_droplet/docs/docker_droplet.ansible.inventory.rst
docker_droplet/docs/docker_droplet.ansible.rst
docker_droplet/docs/docker_droplet.rst
docker_droplet/docs/docker_droplet.terraform.rst
docker_droplet/docs/modules.rst
docker_droplet/terraform/__init__.py
docker_droplet/terraform/digitalocean.jinja2
docker_droplet/terraform/providers.jinja2
docker_droplet/terraform/template.py
docker_droplet/terraform/__pycache__/__init__.cpython-36.pyc
docker_droplet/terraform/__pycache__/template.cpython-36.pyc
docker_droplet/tests/test_interface.py
docker_droplet/tests/test_template.py
docker_droplet/tests/__pycache__/test_interface.cpython-36.pyc
docker_droplet/tests/__pycache__/test_template.cpython-36.pyc
docker_droplet/tests/fixtures/steve.pub
docs/__init__.py
docs/conf.py
tests/__init__.py
docker_droplet-1.0.8.dist-info/LICENSE.md
docker_droplet-1.0.8.dist-info/METADATA
docker_droplet-1.0.8.dist-info/WHEEL
docker_droplet-1.0.8.dist-info/entry_points.txt
docker_droplet-1.0.8.dist-info/top_level.txt
docker_droplet-1.0.8.dist-info/RECORD
