Metadata-Version: 2.1
Name: docker-droplet
Version: 1.0.8
Summary: Create a single digital ocean droplet and provision it to run the docker engine over a simple cli
Home-page: https://github.com/JoelLefkowitz/docker-droplet
Author: Joel Lefkowitz
Author-email: joellefkowitz@hotmail.com
License: MIT
Platform: UNKNOWN
Requires-Python: >= 3.6
Requires-Dist: ansible (>=2.8.0)
Requires-Dist: doboto (>=0.6.1)
Requires-Dist: docopts (>=0.6.1)
Requires-Dist: jinja2 (>=2.11.1)
